lifetime/__init__.py
lifetime/cloud.py
lifetime/me.py
lifetime-0.2.dev0.dist-info/METADATA
lifetime-0.2.dev0.dist-info/RECORD
lifetime-0.2.dev0.dist-info/WHEEL
lifetime-0.2.dev0.dist-info/entry_points.txt
lifetime-0.2.dev0.dist-info/top_level.txt
